binance_sdk_gift_card/__init__.py
binance_sdk_gift_card/gift_card.py
binance_sdk_gift_card/metadata.py
binance_sdk_gift_card/rest_api/__init__.py
binance_sdk_gift_card/rest_api/api/__init__.py
binance_sdk_gift_card/rest_api/api/market_data_api.py
binance_sdk_gift_card/rest_api/models/__init__.py
binance_sdk_gift_card/rest_api/models/create_a_dual_token_gift_card_response.py
binance_sdk_gift_card/rest_api/models/create_a_dual_token_gift_card_response_data.py
binance_sdk_gift_card/rest_api/models/create_a_single_token_gift_card_response.py
binance_sdk_gift_card/rest_api/models/enums.py
binance_sdk_gift_card/rest_api/models/fetch_rsa_public_key_response.py
binance_sdk_gift_card/rest_api/models/fetch_token_limit_response.py
binance_sdk_gift_card/rest_api/models/fetch_token_limit_response_data_inner.py
binance_sdk_gift_card/rest_api/models/redeem_a_binance_gift_card_response.py
binance_sdk_gift_card/rest_api/models/redeem_a_binance_gift_card_response_data.py
binance_sdk_gift_card/rest_api/models/verify_binance_gift_card_by_gift_card_number_response.py
binance_sdk_gift_card/rest_api/models/verify_binance_gift_card_by_gift_card_number_response_data.py
binance_sdk_gift_card/rest_api/rest_api.py
binance_sdk_gift_card-2.2.0.dist-info/METADATA
binance_sdk_gift_card-2.2.0.dist-info/WHEEL
binance_sdk_gift_card-2.2.0.dist-info/licenses/LICENCE
binance_sdk_gift_card-2.2.0.dist-info/RECORD
